[
  {
    "title": "2026-04-24 · Motion-Grounding 4-Way Ablation (E1/E4 × scene-loss × patches-only)",
    "date": "2026-04-24",
    "status": "final",
    "summary": "All 4 cells miss the exit bar; E1 + scene-loss wins (eval 57.9/32.2 mm) but phase-1 decision = NO-IMPROVEMENT vs frozen baseline.",
    "path": "updates/2026-04-24-motion-grounding-4way-ablation.html",
    "file": "updates/2026-04-24-motion-grounding-4way-ablation.html"
  },
  {
    "title": "2026-04-23 · Land the motion-grounding-ablation plan (LoRA + combined motion topology) and run E1/E4 + scene-loss + patches-only-ctx ablations on DexYCB subject-01 single-seq overfit",
    "date": "2026-04-23",
    "status": "wip",
    "summary": "Land the motion-grounding-ablation plan (LoRA + combined motion topology) and run E1/E4 + scene-loss + patches-only-ctx ablations on DexYCB subject-01 single-seq overfit",
    "path": "updates/2026-04-23-session-summary-motion-grounding-lora-ablation-infra.html",
    "file": "updates/2026-04-23-session-summary-motion-grounding-lora-ablation-infra.html",
    "sidecar": "updates/2026-04-23-session-summary-motion-grounding-lora-ablation-infra.json"
  },
  {
    "title": "2026-04-23 · Arm B′ archmatch bs=8 (pt-drxe2i2e)",
    "date": "2026-04-23",
    "status": "final",
    "summary": "Stage-1 single-seq overfit: matched-clip eval 9.64/8.72 mm passes obj, hand marginal. cl=16 OOD regresses to 100/58. GPU mem <40% → bump bs=16 next.",
    "path": "updates/2026-04-23-pt-drxe2i2e-archmatch-bs8.html",
    "file": "updates/2026-04-23-pt-drxe2i2e-archmatch-bs8.html",
    "sidecar": null
  }
]